{"cameraMode":{"drawMode":0,"name":"Shaded","section":"Shading Mode"},"sceneLighting":true,"audioPlay":false,"sceneViewState":{"m_AlwaysRefresh":false,"showFog":true,"showSkybox":true,"showFlares":true,"showImageEffects":true,"showParticleSystems":true,"showVisualEffectGraphs":true,"m_FxEnabled":true},"in2DMode":false,"pivot":{"x":487.49700927734377,"y":98.22047424316406,"z":682.4601440429688},"rotation":{"x":0.09315944463014603,"y":-0.017925892025232316,"z":0.0016802380559965969,"w":0.9955052733421326},"size":666.1300048828125,"orthographic":false}